{
  "a": ["啊", "阿", "哎", "哀", "爱", "嗄"],
  "ai": ["爱", "哀", "矮", "碍", "埃", "唉", "哎"],
  "an": ["安", "暗", "岸", "案", "按", "俺", "氨"],
  "ang": ["昂", "盎", "肮"],
  "ao": ["奥", "傲", "熬", "袄", "凹", "澳", "懊"],
  "ba": ["把", "吧", "爸", "八", "拔", "巴", "疤"],
  "bai": ["白", "百", "拜", "败", "摆", "柏", "佰"],
  "ban": ["半", "办", "班", "版", "般", "搬", "板"],
  "bang": ["帮", "棒", "绑", "傍", "榜", "膀", "磅"],
  "bao": ["报", "包", "抱", "保", "暴", "宝", "薄", "爆"],
  "bei": ["被", "北", "背", "杯", "悲", "备", "倍", "辈"],
  "ben": ["本", "奔", "笨", "苯", "贲"],
  "beng": ["蹦", "崩", "绷", "甭", "泵"],
  "bi": ["比", "笔", "必", "逼", "鼻", "避", "壁", "毕"],
  "bian": ["边", "变", "便", "遍", "编", "辩", "辨", "鞭"],
  "biao": ["表", "标", "彪", "膘", "镖", "飙"],
  "bie": ["别", "憋", "鳖", "瘪"],
  "bin": ["宾", "滨", "彬", "斌", "濒", "殡"],
  "bing": ["并", "病", "兵", "冰", "饼", "丙", "秉"],
  "bo": ["波", "播", "伯", "博", "拨", "薄", "泊", "脖"],
  "bu": ["不", "步", "部", "布", "补", "捕", "哺"],
  "ca": ["擦", "嚓"],
  "cai": ["才", "菜", "采", "财", "材", "猜", "裁", "彩"],
  "can": ["参", "残", "惨", "惭", "蚕", "灿", "餐"],
  "cang": ["藏", "仓", "苍", "沧", "舱"],
  "cao": ["草", "操", "曹", "槽", "糙"],
  "ce": ["测", "策", "侧", "册", "厕"],
  "cen": ["参", "岑", "涔"],
  "ceng": ["层", "曾", "蹭"],
  "cha": ["查", "茶", "差", "插", "察", "叉", "岔"],
  "chai": ["拆", "柴", "差", "豺"],
  "chan": ["产", "缠", "颤", "蝉", "馋", "铲", "禅"],
  "chang": ["长", "常", "场", "唱", "厂", "尝", "偿", "敞"],
  "chao": ["超", "朝", "潮", "抄", "吵", "炒", "巢"],
  "che": ["车", "彻", "扯", "撤", "尘"],
  "chen": ["陈", "晨", "沉", "尘", "称", "衬", "趁", "臣"],
  "cheng": ["成", "城", "程", "称", "承", "诚", "乘", "撑"],
  "chi": ["吃", "持", "迟", "痴", "尺", "齿", "翅", "池"],
  "chong": ["重", "充", "冲", "虫", "崇", "宠"],
  "chou": ["抽", "丑", "臭", "愁", "筹", "仇", "稠"],
  "chu": ["出", "处", "初", "除", "楚", "触", "储", "础"],
  "chua": ["欻"],
  "chuai": ["揣", "踹"],
  "chuan": ["传", "穿", "船", "串", "川", "喘"],
  "chuang": ["窗", "床", "创", "闯", "疮"],
  "chui": ["吹", "垂", "锤", "捶", "炊"],
  "chun": ["春", "纯", "唇", "蠢", "醇"],
  "chuo": ["戳", "绰", "辍", "啜"],
  "ci": ["次", "此", "词", "辞", "刺", "磁", "雌"],
  "cong": ["从", "聪", "丛", "葱", "匆"],
  "cou": ["凑", "辏"],
  "cu": ["粗", "促", "醋", "簇", "卒"],
  "cuan": ["窜", "篡", "蹿", "攒"],
  "cui": ["催", "脆", "翠", "碎", "摧", "粹"],
  "cun": ["村", "存", "寸", "忖"],
  "cuo": ["错", "搓", "挫", "措", "磋"],
  "da": ["大", "打", "达", "搭", "答", "瘩"],
  "dai": ["带", "代", "待", "大", "呆", "袋", "戴", "贷"],
  "dan": ["但", "单", "弹", "淡", "胆", "蛋", "担", "旦"],
  "dang": ["当", "党", "挡", "档", "荡"],
  "dao": ["到", "道", "倒", "刀", "导", "岛", "盗", "稻"],
  "de": ["的", "得", "地", "德"],
  "dei": ["得"],
  "deng": ["等", "灯", "登", "邓", "瞪", "凳", "蹬"],
  "di": ["的", "地", "底", "低", "第", "弟", "敌", "帝"],
  "dian": ["点", "电", "店", "典", "垫", "殿", "淀", "颠"],
  "diao": ["掉", "调", "吊", "钓", "雕", "刁", "叼"],
  "die": ["跌", "叠", "蝶", "爹", "碟", "谍"],
  "ding": ["定", "顶", "丁", "盯", "钉", "订", "鼎"],
  "diu": ["丢", "铥"],
  "dong": ["东", "动", "冬", "懂", "洞", "冻", "栋", "董"],
  "dou": ["都", "斗", "豆", "抖", "兜", "逗", "陡"],
  "du": ["度", "读", "独", "毒", "肚", "堵", "赌", "杜"],
  "duan": ["段", "短", "断", "端", "锻", "缎"],
  "dui": ["对", "队", "堆", "兑", "碓"],
  "dun": ["顿", "吨", "蹲", "盾", "钝", "敦", "墩"],
  "duo": ["多", "朵", "夺", "躲", "堕", "跺", "剁"],
  "e": ["额", "恶", "饿", "鹅", "俄", "呃", "厄"],
  "ei": ["诶", "欸"],
  "en": ["恩", "嗯"],
  "eng": ["鞥"],
  "er": ["而", "耳", "二", "儿", "尔", "饵", "洱"],
  "fa": ["发", "法", "罚", "伐", "阀", "乏", "筏"],
  "fan": ["反", "饭", "犯", "翻", "番", "烦", "范", "泛"],
  "fang": ["方", "放", "房", "防", "访", "仿", "纺", "芳"],
  "fei": ["非", "费", "飞", "肥", "废", "肺", "沸", "匪"],
  "fen": ["分", "份", "粉", "纷", "坟", "奋", "愤", "芬"],
  "feng": ["风", "丰", "封", "峰", "逢", "缝", "疯", "锋"],
  "fo": ["佛"],
  "fou": ["否", "缶"],
  "fu": ["夫", "服", "付", "负", "富", "复", "父", "副"],
  "ga": ["嘎", "噶", "轧"],
  "gai": ["改", "该", "盖", "概", "钙", "溉"],
  "gan": ["干", "感", "赶", "敢", "肝", "甘", "杆", "竿"],
  "gang": ["刚", "钢", "港", "纲", "岗", "缸", "杠"],
  "gao": ["高", "搞", "告", "稿", "糕", "膏"],
  "ge": ["个", "各", "歌", "格", "隔", "革", "割", "阁"],
  "gei": ["给"],
  "gen": ["根", "跟", "亘", "艮"],
  "geng": ["更", "耕", "梗", "颈", "庚", "羹"],
  "gong": ["工", "公", "共", "功", "宫", "供", "攻", "恭"],
  "gou": ["够", "狗", "沟", "钩", "构", "购", "勾"],
  "gu": ["古", "故", "谷", "骨", "鼓", "股", "固", "顾"],
  "gua": ["挂", "刮", "瓜", "寡", "卦"],
  "guai": ["怪", "乖", "拐"],
  "guan": ["关", "管", "官", "观", "馆", "冠", "惯", "灌"],
  "guang": ["光", "广", "逛"],
  "gui": ["贵", "归", "鬼", "桂", "柜", "规", "轨", "跪"],
  "gun": ["滚", "棍", "辊"],
  "guo": ["国", "果", "过", "锅", "裹", "郭"],
  "ha": ["哈", "蛤"],
  "hai": ["还", "海", "害", "孩", "嗨", "骸", "氦"],
  "han": ["汉", "含", "寒", "喊", "汗", "韩", "函", "翰"],
  "hang": ["行", "航", "杭", "巷"],
  "hao": ["好", "号", "毫", "豪", "郝", "浩", "耗", "壕"],
  "he": ["和", "河", "喝", "核", "合", "何", "贺", "盒"],
  "hei": ["黑", "嘿", "嗨"],
  "hen": ["很", "狠", "恨", "痕"],
  "heng": ["横", "衡", "恒", "哼"],
  "hong": ["红", "宏", "洪", "虹", "鸿", "轰", "烘"],
  "hou": ["后", "候", "厚", "猴", "喉", "侯", "吼"],
  "hu": ["湖", "虎", "护", "呼", "户", "胡", "壶", "互"],
  "hua": ["花", "化", "话", "画", "华", "划", "滑"],
  "huai": ["坏", "怀", "淮", "槐", "徊"],
  "huan": ["还", "换", "欢", "环", "幻", "患", "缓", "唤"],
  "huang": ["黄", "皇", "荒", "慌", "晃", "恍", "煌", "簧"],
  "hui": ["会", "回", "灰", "挥", "汇", "辉", "毁", "慧"],
  "hun": ["混", "婚", "魂", "浑", "昏", "荤"],
  "huo": ["或", "火", "活", "货", "获", "伙", "祸", "惑"],
  "ji": ["几", "机", "及", "己", "记", "技", "际", "计"],
  "jia": ["家", "加", "假", "价", "夹", "甲", "嫁", "驾"],
  "jian": ["见", "间", "件", "建", "简", "坚", "健", "剑"],
  "jiang": ["将", "讲", "江", "降", "奖", "疆", "酱", "蒋"],
  "jiao": ["叫", "教", "脚", "角", "交", "较", "觉", "浇"],
  "jie": ["解", "接", "结", "节", "姐", "街", "借", "界"],
  "jin": ["进", "近", "金", "今", "仅", "尽", "紧", "禁"],
  "jing": ["经", "精", "景", "京", "静", "惊", "竞", "净"],
  "jiong": ["窘", "迥", "炯"],
  "jiu": ["就", "旧", "九", "久", "救", "酒", "举", "究"],
  "ju": ["举", "具", "句", "局", "据", "距", "剧", "巨"],
  "juan": ["卷", "圈", "捐", "娟", "倦", "绢"],
  "jue": ["觉", "决", "绝", "角", "掘", "爵", "诀"],
  "jun": ["军", "均", "君", "菌", "俊", "骏"],
  "ka": ["卡", "咖", "喀", "咔"],
  "kai": ["开", "凯", "揩", "慨", "楷"],
  "kan": ["看", "砍", "坎", "刊", "堪", "勘"],
  "kang": ["抗", "康", "扛", "炕", "慷"],
  "kao": ["考", "靠", "烤", "拷", "铐"],
  "ke": ["可", "课", "科", "客", "刻", "克", "棵", "渴"],
  "ken": ["肯", "啃", "垦", "恳"],
  "keng": ["坑", "铿", "吭"],
  "kong": ["空", "孔", "恐", "控"],
  "kou": ["口", "扣", "寇", "叩", "抠"],
  "ku": ["苦", "哭", "酷", "库", "裤", "窟", "枯"],
  "kua": ["夸", "跨", "垮", "挎"],
  "kuai": ["快", "块", "筷", "会", "侩"],
  "kuan": ["宽", "款"],
  "kuang": ["况", "矿", "框", "狂", "旷", "眶", "筐"],
  "kui": ["亏", "溃", "愧", "盔", "窥", "葵", "魁"],
  "kun": ["困", "昆", "捆", "坤"],
  "kuo": ["扩", "阔", "括", "廓"],
  "la": ["拉", "啦", "辣", "蜡", "腊", "喇"],
  "lai": ["来", "赖", "莱", "睐", "癞"],
  "lan": ["蓝", "兰", "拦", "栏", "懒", "烂", "篮", "揽"],
  "lang": ["浪", "狼", "朗", "郎", "廊", "琅"],
  "lao": ["老", "劳", "牢", "姥", "捞", "烙", "酪"],
  "le": ["了", "乐", "勒", "肋"],
  "lei": ["类", "累", "雷", "泪", "蕾", "垒", "擂"],
  "leng": ["冷", "楞", "愣"],
  "li": ["里", "理", "力", "例", "利", "离", "立", "丽"],
  "lia": ["俩"],
  "lian": ["联", "练", "脸", "链", "连", "莲", "帘", "怜"],
  "liang": ["两", "亮", "量", "良", "凉", "粮", "梁", "辆"],
  "liao": ["了", "料", "聊", "辽", "疗", "撩", "燎"],
  "lie": ["列", "裂", "烈", "猎", "劣", "趔"],
  "lin": ["林", "临", "邻", "淋", "琳", "磷", "鳞"],
  "ling": ["领", "令", "灵", "零", "另", "铃", "岭", "凌"],
  "liu": ["六", "流", "留", "刘", "柳", "溜", "瘤"],
  "long": ["龙", "笼", "隆", "弄", "聋", "拢", "垄"],
  "lou": ["楼", "露", "漏", "搂", "陋", "篓"],
  "lu": ["路", "陆", "露", "录", "绿", "鲁", "炉", "鹿"],
  "luan": ["乱", "卵", "滦", "峦"],
  "lun": ["论", "轮", "伦", "沦"],
  "luo": ["落", "罗", "洛", "络", "螺", "骡", "裸"],
  "lv": ["绿", "律", "旅", "虑", "率", "铝", "滤", "吕"],
  "ma": ["吗", "妈", "马", "麻", "骂", "码", "蚂"],
  "mai": ["买", "卖", "麦", "迈", "埋", "脉"],
  "man": ["满", "慢", "漫", "蛮", "瞒", "馒", "蔓"],
  "mang": ["忙", "盲", "茫", "芒", "莽"],
  "mao": ["毛", "猫", "帽", "冒", "茂", "贸", "矛", "锚"],
  "me": ["么", "嚜"],
  "mei": ["没", "美", "每", "妹", "煤", "梅", "眉", "霉"],
  "men": ["们", "门", "闷", "焖"],
  "meng": ["梦", "猛", "蒙", "孟", "盟", "萌", "朦"],
  "mi": ["米", "密", "迷", "秘", "蜜", "眯", "谜", "弥"],
  "mian": ["面", "免", "棉", "眠", "绵", "缅", "勉"],
  "miao": ["妙", "苗", "秒", "描", "瞄", "庙", "渺"],
  "mie": ["灭", "蔑", "咩"],
  "min": ["民", "敏", "闽", "皿", "抿", "悯"],
  "ming": ["明", "名", "命", "鸣", "茗", "铭", "冥"],
  "miu": ["谬", "缪"],
  "mo": ["没", "么", "磨", "模", "摸", "墨", "莫", "默"],
  "mou": ["某", "谋", "牟", "眸"],
  "mu": ["木", "目", "母", "墓", "幕", "牧", "慕", "暮"],
  "na": ["那", "拿", "哪", "纳", "娜", "呐"],
  "nai": ["奶", "乃", "耐", "奈", "鼐"],
  "nan": ["南", "难", "男", "楠"],
  "nang": ["囊", "馕"],
  "nao": ["脑", "闹", "恼", "挠"],
  "ne": ["呢", "讷", "哪"],
  "nei": ["内", "那", "馁"],
  "nen": ["嫩"],
  "neng": ["能"],
  "ni": ["你", "尼", "泥", "拟", "逆", "匿", "腻"],
  "nian": ["年", "念", "粘", "鲶", "碾", "撵"],
  "niang": ["娘", "酿"],
  "niao": ["鸟", "尿"],
  "nie": ["捏", "聂", "镊", "孽", "蹑"],
  "nin": ["您", "佞"],
  "ning": ["宁", "凝", "柠", "拧", "狞"],
  "niu": ["牛", "扭", "纽", "钮"],
  "nong": ["农", "浓", "弄"],
  "nou": ["耨"],
  "nu": ["女", "怒", "努", "奴"],
  "nuan": ["暖"],
  "nuo": ["挪", "诺", "糯", "懦"],
  "nv": ["女"],
  "o": ["哦", "噢", "喔"],
  "ou": ["偶", "欧", "呕", "鸥", "殴", "藕"],
  "pa": ["怕", "爬", "拍", "帕", "趴", "扒", "琶"],
  "pai": ["排", "派", "拍", "牌", "徘", "湃"],
  "pan": ["盘", "判", "盼", "攀", "潘", "叛", "畔"],
  "pang": ["旁", "胖", "庞", "磅", "螃"],
  "pao": ["跑", "泡", "抛", "炮", "袍", "刨"],
  "pei": ["配", "陪", "培", "佩", "赔", "沛", "裴"],
  "pen": ["盆", "喷"],
  "peng": ["朋", "碰", "捧", "彭", "蓬", "棚", "膨", "鹏"],
  "pi": ["皮", "批", "屁", "匹", "片", "劈", "脾", "疲"],
  "pian": ["片", "篇", "偏", "骗", "便", "翩"],
  "piao": ["票", "飘", "漂", "瓢", "嫖"],
  "pie": ["撇", "瞥"],
  "pin": ["品", "拼", "贫", "频", "聘"],
  "ping": ["平", "评", "瓶", "凭", "苹", "屏", "萍", "乒"],
  "po": ["破", "坡", "婆", "颇", "泊", "迫", "魄"],
  "pu": ["普", "铺", "朴", "浦", "谱", "扑", "仆", "葡"],
  "qi": ["起", "其", "气", "七", "期", "齐", "奇", "器"],
  "qia": ["恰", "掐", "卡", "洽"],
  "qian": ["前", "千", "钱", "浅", "签", "牵", "铅", "欠"],
  "qiang": ["强", "墙", "枪", "抢", "腔", "呛"],
  "qiao": ["桥", "巧", "敲", "瞧", "悄", "翘", "乔", "俏"],
  "qie": ["切", "且", "窃", "茄", "怯", "惬"],
  "qin": ["亲", "琴", "勤", "侵", "秦", "寝", "沁"],
  "qing": ["请", "清", "情", "青", "轻", "庆", "晴", "倾"],
  "qiong": ["穷", "琼", "邛"],
  "qiu": ["秋", "球", "求", "丘", "邱", "囚", "酋"],
  "qu": ["去", "取", "区", "曲", "趣", "渠", "趋", "娶"],
  "quan": ["全", "权", "圈", "泉", "拳", "犬", "劝"],
  "que": ["却", "确", "缺", "雀", "鹊", "瘸"],
  "qun": ["群", "裙"],
  "ran": ["然", "染", "燃", "冉"],
  "rang": ["让", "嚷", "壤", "攘"],
  "rao": ["绕", "饶", "扰"],
  "re": ["热", "惹"],
  "ren": ["人", "认", "忍", "仁", "任", "韧", "刃"],
  "reng": ["仍", "扔"],
  "ri": ["日"],
  "rong": ["容", "荣", "融", "溶", "绒", "蓉", "榕"],
  "rou": ["肉", "柔", "揉", "蹂"],
  "ru": ["如", "入", "乳", "儒", "辱", "褥"],
  "ruan": ["软", "阮"],
  "rui": ["瑞", "锐", "睿", "蕊"],
  "run": ["润", "闰"],
  "ruo": ["若", "弱", "偌"],
  "sa": ["撒", "洒", "萨"],
  "sai": ["赛", "塞", "腮"],
  "san": ["三", "散", "伞", "叁"],
  "sang": ["桑", "丧", "嗓", "搡"],
  "sao": ["扫", "嫂", "骚", "臊"],
  "se": ["色", "涩", "瑟"],
  "sen": ["森"],
  "seng": ["僧"],
  "sha": ["杀", "沙", "傻", "啥", "砂", "纱", "刹"],
  "shai": ["晒", "筛"],
  "shan": ["山", "善", "闪", "扇", "珊", "衫", "杉", "删"],
  "shang": ["上", "商", "伤", "尚", "赏", "裳"],
  "shao": ["少", "烧", "稍", "哨", "勺", "韶", "邵"],
  "she": ["社", "设", "射", "蛇", "摄", "舍", "涉", "奢"],
  "shei": ["谁"],
  "shen": ["什", "深", "身", "神", "甚", "审", "沈", "伸"],
  "sheng": ["生", "声", "省", "胜", "圣", "盛", "剩", "升"],
  "shi": ["是", "时", "事", "市", "式", "使", "世", "示"],
  "shou": ["手", "收", "受", "首", "守", "瘦", "兽", "寿"],
  "shu": ["书", "树", "数", "属", "输", "熟", "术", "束"],
  "shua": ["刷", "耍", "唰"],
  "shuai": ["帅", "摔", "甩", "衰"],
  "shuan": ["栓", "拴", "涮"],
  "shuang": ["双", "爽", "霜"],
  "shui": ["水", "睡", "谁", "税"],
  "shun": ["顺", "瞬", "舜", "吮"],
  "shuo": ["说", "朔", "硕", "烁"],
  "si": ["四", "死", "思", "似", "私", "司", "丝", "寺"],
  "song": ["送", "松", "宋", "颂", "诵", "耸"],
  "sou": ["搜", "嗖", "叟", "艘"],
  "su": ["素", "速", "苏", "诉", "俗", "宿", "塑", "肃"],
  "suan": ["算", "酸", "蒜"],
  "sui": ["随", "岁", "虽", "碎", "遂", "穗", "隧"],
  "sun": ["孙", "损", "笋", "荪"],
  "suo": ["所", "锁", "缩", "索", "梭"],
  "ta": ["他", "她", "它", "塔", "踏", "榻", "蹋"],
  "tai": ["太", "台", "态", "抬", "泰", "胎", "苔"],
  "tan": ["谈", "弹", "碳", "探", "叹", "摊", "坛", "贪"],
  "tang": ["堂", "糖", "汤", "唐", "躺", "趟", "塘", "烫"],
  "tao": ["套", "逃", "桃", "讨", "陶", "淘", "涛"],
  "te": ["特"],
  "teng": ["疼", "腾", "藤", "滕"],
  "ti": ["提", "体", "题", "替", "踢", "剃", "啼", "梯"],
  "tian": ["天", "田", "甜", "填", "添", "舔"],
  "tiao": ["条", "跳", "调", "挑", "挑"],
  "tie": ["铁", "贴", "帖"],
  "ting": ["听", "停", "厅", "挺", "庭", "亭", "艇"],
  "tong": ["同", "通", "统", "痛", "童", "铜", "桶", "筒"],
  "tou": ["头", "投", "偷", "透", "骰"],
  "tu": ["土", "图", "突", "吐", "兔", "涂", "途", "屠"],
  "tuan": ["团", "湍", "抟"],
  "tui": ["退", "推", "腿", "颓", "蜕"],
  "tun": ["吞", "屯", "臀", "囤"],
  "tuo": ["脱", "拖", "托", "妥", "驼", "拓", "椭"],
  "wa": ["挖", "哇", "瓦", "娃", "蛙", "洼", "袜"],
  "wai": ["外", "歪"],
  "wan": ["万", "完", "晚", "碗", "弯", "玩", "湾", "丸"],
  "wang": ["王", "往", "忘", "望", "网", "汪"],
  "wei": ["为", "位", "未", "味", "微", "围", "卫", "伟"],
  "wen": ["问", "文", "闻", "温", "稳", "吻", "纹"],
  "weng": ["翁", "嗡", "瓮"],
  "wo": ["我", "卧", "握", "窝", "涡"],
  "wu": ["五", "无", "物", "屋", "武", "误", "务", "雾"],
  "xi": ["西", "习", "系", "细", "希", "席", "洗", "喜"],
  "xia": ["下", "夏", "吓", "虾", "瞎", "侠", "峡", "狭"],
  "xian": ["现", "先", "显", "线", "县", "鲜", "险", "限"],
  "xiang": ["想", "向", "像", "相", "香", "乡", "响", "箱"],
  "xiao": ["小", "笑", "校", "消", "晓", "肖", "效", "萧"],
  "xie": ["谢", "写", "些", "鞋", "协", "血", "斜", "歇"],
  "xin": ["心", "新", "信", "欣", "辛", "薪", "芯"],
  "xing": ["行", "性", "星", "形", "型", "姓", "兴", "醒"],
  "xiong": ["熊", "胸", "兄", "凶", "匈", "雄"],
  "xiu": ["修", "休", "秀", "袖", "绣", "朽", "嗅"],
  "xu": ["许", "需", "续", "虚", "序", "绪", "蓄", "叙"],
  "xuan": ["选", "宣", "旋", "悬", "玄", "轩", "喧", "渲"],
  "xue": ["学", "雪", "血", "穴", "薛", "靴"],
  "xun": ["训", "寻", "讯", "迅", "巡", "循", "殉", "熏"],
  "ya": ["呀", "压", "牙", "哑", "鸦", "鸭", "崖", "芽"],
  "yan": ["眼", "烟", "言", "颜", "严", "沿", "盐", "演"],
  "yang": ["样", "阳", "养", "洋", "央", "羊", "扬", "杨"],
  "yao": ["要", "药", "摇", "遥", "咬", "腰", "邀", "钥"],
  "ye": ["也", "业", "夜", "页", "叶", "野", "爷"],
  "yi": ["一", "以", "已", "意", "义", "易", "亿", "衣"],
  "yin": ["因", "银", "引", "印", "音", "隐", "饮", "阴"],
  "ying": ["应", "影", "营", "英", "迎", "硬", "赢", "映"],
  "yo": ["哟", "唷"],
  "yong": ["用", "永", "勇", "拥", "涌", "踊", "庸", "雍"],
  "you": ["有", "又", "友", "由", "游", "油", "优", "右"],
  "yu": ["与", "于", "鱼", "雨", "语", "玉", "欲", "余"],
  "yuan": ["元", "原", "远", "院", "源", "圆", "愿", "缘"],
  "yue": ["月", "越", "约", "乐", "岳", "阅", "跃", "悦"],
  "yun": ["云", "运", "允", "晕", "韵", "孕", "蕴"],
  "za": ["杂", "扎", "砸", "咋"],
  "zai": ["在", "再", "载", "宰", "灾", "栽", "哉"],
  "zan": ["咱", "赞", "攒", "暂", "簪"],
  "zang": ["脏", "葬", "藏", "赃"],
  "zao": ["早", "造", "遭", "枣", "灶", "糟", "澡", "燥"],
  "ze": ["则", "责", "择", "泽"],
  "zei": ["贼"],
  "zen": ["怎", "谮"],
  "zeng": ["增", "曾", "赠", "憎"],
  "zha": ["扎", "炸", "渣", "榨", "闸", "眨", "诈", "乍"],
  "zhai": ["摘", "宅", "窄", "债", "寨", "斋"],
  "zhan": ["站", "战", "占", "展", "沾", "粘", "斩", "崭"],
  "zhang": ["长", "张", "章", "掌", "涨", "丈", "帐", "障"],
  "zhao": ["找", "照", "着", "招", "朝", "赵", "罩", "兆"],
  "zhe": ["这", "者", "折", "哲", "遮", "着", "浙"],
  "zhei": ["这"],
  "zhen": ["真", "针", "镇", "振", "阵", "珍", "诊", "枕"],
  "zheng": ["正", "整", "政", "争", "证", "征", "睁", "蒸"],
  "zhi": ["知", "之", "只", "支", "直", "值", "志", "制"],
  "zhong": ["中", "重", "众", "种", "终", "钟", "忠"],
  "zhou": ["周", "州", "洲", "粥", "舟", "皱", "肘", "轴"],
  "zhu": ["主", "住", "助", "祝", "注", "猪", "竹", "柱"],
  "zhua": ["抓", "爪"],
  "zhuai": ["拽"],
  "zhuan": ["转", "专", "赚", "砖", "传", "撰"],
  "zhuang": ["装", "壮", "庄", "撞", "妆", "桩"],
  "zhui": ["追", "坠", "缀", "锥", "赘"],
  "zhun": ["准", "谆"],
  "zhuo": ["着", "桌", "捉", "卓", "灼", "浊", "酌"],
  "zi": ["子", "自", "字", "资", "紫", "仔", "姿", "滋"],
  "zong": ["总", "宗", "综", "纵", "棕", "踪"],
  "zou": ["走", "奏", "揍", "邹"],
  "zu": ["组", "族", "足", "祖", "阻", "租"],
  "zuan": ["钻", "纂", "攥"],
  "zui": ["最", "嘴", "醉", "罪", "碎"],
  "zun": ["尊", "遵", "撙"],
  "zuo": ["做", "坐", "左", "座", "作", "昨"]
}
